{"nodes": [{"id": "axis", "label": "Axis.js", "file_type": "code", "source_file": "materials/labs/SmallProjects/dojo/src/charting/vml/Axis.js", "source_location": "L1"}, {"id": "axis_createlabel", "label": "createLabel()", "file_type": "code", "source_file": "materials/labs/SmallProjects/dojo/src/charting/vml/Axis.js", "source_location": "L116"}], "edges": [{"source": "axis", "target": "axis_createlabel", "relation": "contains", "confidence": "EXTRACTED", "source_file": "materials/labs/SmallProjects/dojo/src/charting/vml/Axis.js", "source_location": "L116", "weight": 1.0}]}